recognizer/__init__.py
recognizer/agents/__init__.py
recognizer/agents/playwright/__init__.py
recognizer/agents/playwright/async_control.py
recognizer/agents/playwright/sync_control.py
recognizer/components/__init__.py
recognizer/components/detection_processor.py
recognizer/components/detector.py
recognizer/components/image_processor.py
recognizer/components/prompt_handler.py
recognizer-1.4.dist-info/LICENSE
recognizer-1.4.dist-info/METADATA
recognizer-1.4.dist-info/WHEEL
recognizer-1.4.dist-info/top_level.txt
recognizer-1.4.dist-info/RECORD
