Metadata-Version: 2.1
Name: recognizer
Version: 1.4
Summary: 🦉Gracefully face reCAPTCHA challenge with ultralytics YOLOv8-seg, CLIPs VIT-B/16 and CLIP-Seg/RD64. Implemented in playwright or an easy-to-use API.
Home-page: https://github.com/Vinyzu/recognizer
Author: Vinyzu
License: GNU General Public License v3.0
Project-URL: Source, https://github.com/Vinyzu/reCognizer
Project-URL: Tracker, https://github.com/Vinyzu/reCognizer/issues
Keywords: botright,playwright,browser,automation,fingerprints,fingerprinting,dataset,data,recaptcha,captcha
Classifier: Topic :: Scientific/Engineering
Classifier: Topic :: Scientific/Engineering :: Artificial Intelligence
Classifier: Topic :: Software Development
Classifier: Topic :: Software Development :: Libraries
Classifier: Topic :: Software Development :: Libraries :: Python Modules
Classifier: Topic :: Internet :: WWW/HTTP :: Browsers
Classifier: License :: OSI Approved :: Apache Software License
Classifier: Programming Language :: Python :: 3
Requires-Python: >=3.8
License-File: LICENSE
Requires-Dist: opencv-python
Requires-Dist: imageio
Requires-Dist: ultralytics
Requires-Dist: transformers
Requires-Dist: numpy
Requires-Dist: playwright
Provides-Extra: testing
Requires-Dist: pytest ; extra == 'testing'
Requires-Dist: mypy ; extra == 'testing'
Requires-Dist: flake8 ; extra == 'testing'
Requires-Dist: black ; extra == 'testing'
Requires-Dist: isort ; extra == 'testing'
